randomsearch/__init__.py
randomsearch/randomsearch.py
randomsearch-0.0.1.dist-info/LICENSE
randomsearch-0.0.1.dist-info/METADATA
randomsearch-0.0.1.dist-info/WHEEL
randomsearch-0.0.1.dist-info/top_level.txt
randomsearch-0.0.1.dist-info/RECORD
