Metadata-Version: 2.1
Name: randomsearch
Version: 0.0.1
Summary: A simple n-dimensional random search algorithm
Home-page: https://github.com/angelgaspar/randomsearch
Author: Angel Gaspar
Author-email: engineer.angel.gaspar@gmail.com
License: UNKNOWN
Keywords: randomsearch,random search,optimization,algorithm
Platform: UNKNOWN
Classifier: Programming Language :: Python :: 3
Classifier: License :: OSI Approved :: MIT License
Classifier: Operating System :: OS Independent
Requires-Python: >=3.6
Requires-Dist: numpy
